README.md
setup.py
ichoose_device/__init__.py
ichoose_device.egg-info/PKG-INFO
ichoose_device.egg-info/SOURCES.txt
ichoose_device.egg-info/dependency_links.txt
ichoose_device.egg-info/entry_points.txt
ichoose_device.egg-info/requires.txt
ichoose_device.egg-info/top_level.txt