Metadata-Version: 2.1
Name: ichoose-device
Version: 1.0.1
Summary: Interactivly choose which adb device you want to work with in the current shell session
Author: Almog Manor
Author-email: ManorAlmog@outlook.com
Requires-Python: >=3.7
